{
  "project_info": {
    "project_number": "510368523955",
    "project_id": "firefly-b98c5",
    "storage_bucket": "firefly-b98c5.appspot.com"
  },
  "client": [
    {
      "client_info": {
        "mobilesdk_app_id": "1:510368523955:android:7fa8eb610a92e600beb2c6",
        "android_client_info": {
          "package_name": "com.example.firefly_task"
        }
      },
      "oauth_client": [],
      "api_key": [
        {
          "current_key": "AIzaSyAbRCdeDb1XmbjYAtBag8BxJKea1U7rmjw"
        }
      ],
      "services": {
        "appinvite_service": {
          "other_platform_oauth_client": []
        }
      }
    }
  ],
  "configuration_version": "1"
}